fantel_package/__init__.py
fantel_package/script.py
fantel_package-0.1.dist-info/METADATA
fantel_package-0.1.dist-info/WHEEL
fantel_package-0.1.dist-info/entry_points.txt
fantel_package-0.1.dist-info/top_level.txt
fantel_package-0.1.dist-info/RECORD
